python_dhl/__init__.py
python_dhl/service.py
python_dhl/resources/__init__.py
python_dhl/resources/address.py
python_dhl/resources/helper.py
python_dhl/resources/response.py
python_dhl/resources/shipment.py
python_dhl_api-3.0.1.dist-info/licenses/LICENSE
python_dhl_api-3.0.1.dist-info/METADATA
python_dhl_api-3.0.1.dist-info/WHEEL
python_dhl_api-3.0.1.dist-info/top_level.txt
python_dhl_api-3.0.1.dist-info/RECORD
