Metadata-Version: 2.4
Name: python-dhl-api
Version: 3.0.1
Summary: A Python module to integrate with DHL courier
Author-email: Innove <info@innove.it>
License: MIT
Classifier: Programming Language :: Python :: 3
Classifier: Programming Language :: Python :: 3.12
Classifier: License :: OSI Approved :: MIT License
Classifier: Operating System :: OS Independent
Requires-Python: >=3.12
License-File: LICENSE
Requires-Dist: requests
Requires-Dist: urllib3>=2.6.2
Dynamic: license-file
